{
  "normal": {
    "400": "https://fonts.gstatic.com/l/font?kit=e3tmeuGtX-Co5MNzeAOqinEQcknQ&skey=4aba808beb02377b&v=v13#AbhayaLibre",
    "500": "https://fonts.gstatic.com/l/font?kit=e3t5euGtX-Co5MNzeAOqinEYj2rCo9ZO&skey=c9f234d72fbefdc5&v=v13#AbhayaLibre",
    "600": "https://fonts.gstatic.com/l/font?kit=e3t5euGtX-Co5MNzeAOqinEYo23Co9ZO&skey=7806b586edfb51c5&v=v13#AbhayaLibre",
    "700": "https://fonts.gstatic.com/l/font?kit=e3t5euGtX-Co5MNzeAOqinEYx2zCo9ZO&skey=236daab164e65f82&v=v13#AbhayaLibre",
    "800": "https://fonts.gstatic.com/l/font?kit=e3t5euGtX-Co5MNzeAOqinEY22_Co9ZO&skey=e1f8d1be735feb1c&v=v13#AbhayaLibre"
  }
}